delphai_discovery/__init__.py
delphai_discovery-0.1.6.dist-info/WHEEL
delphai_discovery-0.1.6.dist-info/METADATA
delphai_discovery-0.1.6.dist-info/RECORD
