Metadata-Version: 2.1
Name: delphai-discovery
Version: 0.1.6
Summary: delphai microservice discovery
Author: Barath Kumar
Author-email: barath@delphai.com
Requires-Python: >=3.8,<4.0
Classifier: Programming Language :: Python :: 3
Classifier: Programming Language :: Python :: 3.8
Requires-Dist: grpcio (>=1.35.0,<2.0.0)
Requires-Dist: grpcio-reflection (>=1.35.0,<2.0.0)
Requires-Dist: httpx[http2] (>=0.16.1,<0.17.0)
Requires-Dist: python-consul (>=1.1.0,<2.0.0)
